wemplate/__init__.py
wemplate/wemplate.py
wemplate/wempy.py
wempy-0.2.1.data/scripts/wempy
wempy-0.2.1.dist-info/LICENSE
wempy-0.2.1.dist-info/LICENSE.wiki
wempy-0.2.1.dist-info/METADATA
wempy-0.2.1.dist-info/WHEEL
wempy-0.2.1.dist-info/top_level.txt
wempy-0.2.1.dist-info/RECORD
